vps/__init__.py
vps/client.py
vps/configer.py
vps/db.py
vps/installer.py
vps/meta.py
vps/osi.py
vps/piper.py
vps/primeproducer.py
vps/status.py
vps/apps/__init__.py
vps/apps/sysstat.py
vps/auth/__init__.py
vps/auth/accounts.py
vps/bash_scripts/__init__.py
vps/data/cauth
vps/data/gost.sh
vps/netflix/__init__.py
vps/netflix/find_good_ip.py
vpscli-0.3.15.dist-info/LICENSE
vpscli-0.3.15.dist-info/METADATA
vpscli-0.3.15.dist-info/WHEEL
vpscli-0.3.15.dist-info/entry_points.txt
vpscli-0.3.15.dist-info/top_level.txt
vpscli-0.3.15.dist-info/RECORD
